interceptor/__init__.py
interceptor/interceptor.py
py_interceptor-0.1.0.dist-info/LICENSE
py_interceptor-0.1.0.dist-info/METADATA
py_interceptor-0.1.0.dist-info/WHEEL
py_interceptor-0.1.0.dist-info/top_level.txt
py_interceptor-0.1.0.dist-info/RECORD
