Metadata-Version: 2.2
Name: py-interceptor
Version: 0.1.0
Summary: A library for intercepting and processing Python method calls.
Author-email: RustyTuna <prototype4711@gmail.com>
Project-URL: Documentation, https://github.com/RustyTunaDev/py-interceptor#readme
Project-URL: Issues, https://github.com/RustyTunaDev/py-interceptor#readme/-/issues
Project-URL: Source, https://github.com/RustyTunaDev/py-interceptor#readme/src
Keywords: mocking,testing
Classifier: Programming Language :: Python :: 3 :: Only
Classifier: Programming Language :: Python :: Implementation :: CPython
Classifier: Programming Language :: Python :: Implementation :: PyPy
Requires-Python: >=3.9
License-File: LICENSE
Provides-Extra: dev
Requires-Dist: pytest; extra == "dev"
Requires-Dist: build; extra == "dev"
